finnews/client.py
finnews/cnbc.py
finnews/cnn_finance.py
finnews/fields.py
finnews/market_watch.py
finnews/nasdaq.py
finnews/news_enum.py
finnews/parser.py
finnews/seeking_alpha.py
finnews/sp_global.py
finnews/wsj.py
finnews/yahoo_finance.py
fin_news-0.1.2.dist-info/LICENSE
fin_news-0.1.2.dist-info/METADATA
fin_news-0.1.2.dist-info/WHEEL
fin_news-0.1.2.dist-info/top_level.txt
fin_news-0.1.2.dist-info/RECORD
