Metadata-Version: 2.1
Name: fin-news
Version: 0.1.2
Summary: A finance news aggregator used to collect articles on different market topics.
Home-page: https://github.com/areed1192/finance-news-aggregator
Author: Alex Reed
Author-email: coding.sigma@gmail.com
License: UNKNOWN
Platform: UNKNOWN
Classifier: Development Status :: 3 - Alpha
Classifier: Intended Audience :: Financial and Insurance Industry
Classifier: License :: OSI Approved :: MIT License
Classifier: Natural Language :: English
Classifier: Operating System :: OS Independent
Classifier: Programming Language :: Python :: 3
Requires-Python: >3.7
License-File: LICENSE
Requires-Dist: requests (>=2.24.0)
Requires-Dist: fake-useragent (==0.1.11)
